odoo10_addon_hr_attendance_autoclose-10.0.1.0.0.99.dev5-py3.8-nspkg.pth
odoo/addons/hr_attendance_autoclose/README.rst
odoo/addons/hr_attendance_autoclose/__init__.py
odoo/addons/hr_attendance_autoclose/__manifest__.py
odoo/addons/hr_attendance_autoclose/data/hr_attendance.xml
odoo/addons/hr_attendance_autoclose/data/hr_attendance_reason.xml
odoo/addons/hr_attendance_autoclose/i18n/hr_attendance_autoclose.pot
odoo/addons/hr_attendance_autoclose/models/__init__.py
odoo/addons/hr_attendance_autoclose/models/hr_attendance.py
odoo/addons/hr_attendance_autoclose/models/res_company.py
odoo/addons/hr_attendance_autoclose/readme/CONTRIBUTORS.rst
odoo/addons/hr_attendance_autoclose/readme/DESCRIPTION.rst
odoo/addons/hr_attendance_autoclose/readme/USAGE.rst
odoo/addons/hr_attendance_autoclose/static/description/icon.png
odoo/addons/hr_attendance_autoclose/static/description/index.html
odoo/addons/hr_attendance_autoclose/tests/__init__.py
odoo/addons/hr_attendance_autoclose/tests/test_hr_attendance_auto_close.py
odoo/addons/hr_attendance_autoclose/views/hr_attendance_view.xml
odoo/addons/hr_attendance_autoclose/views/res_company_view.xml
odoo10_addon_hr_attendance_autoclose-10.0.1.0.0.99.dev5.dist-info/METADATA
odoo10_addon_hr_attendance_autoclose-10.0.1.0.0.99.dev5.dist-info/WHEEL
odoo10_addon_hr_attendance_autoclose-10.0.1.0.0.99.dev5.dist-info/namespace_packages.txt
odoo10_addon_hr_attendance_autoclose-10.0.1.0.0.99.dev5.dist-info/top_level.txt
odoo10_addon_hr_attendance_autoclose-10.0.1.0.0.99.dev5.dist-info/RECORD
